csnanalysis/__init__.py
csnanalysis/csn.py
csnanalysis/matrix.py
csnanalysis-0.6.0.dist-info/licenses/LICENSE.txt
csnanalysis-0.6.0.dist-info/METADATA
csnanalysis-0.6.0.dist-info/WHEEL
csnanalysis-0.6.0.dist-info/top_level.txt
csnanalysis-0.6.0.dist-info/RECORD
