Metadata-Version: 2.4
Name: CSNAnalysis
Version: 0.6.0
Summary: Tools for creating, analyzing and visualizing Conformation Space Networks.
Home-page: https://github.com/ADicksonLab/CSNAnalysis
Author: Alex Dickson
Author-email: alexrd@msu.edu
License: MIT
Classifier: Topic :: Utilities
Classifier: License :: OSI Approved :: MIT License
Classifier: Programming Language :: Python :: 3
License-File: LICENSE.txt
Requires-Dist: numpy
Requires-Dist: networkx>=2.1
Requires-Dist: scipy>=0.19
Dynamic: author
Dynamic: author-email
Dynamic: classifier
Dynamic: home-page
Dynamic: license
Dynamic: license-file
Dynamic: requires-dist
Dynamic: summary
